{
    "id": 7075,
    "video_id": "etvQ528_seY",
    "show_name": "Shorts",
    "hosts": [
        "Nick Scarpino",
        "Andy Cortez",
        "Mike Howard"
    ],
    "title": "Kevin and Andy are MAD in Mythforce. #shorts",
    "description": "From this stream: https://www.youtube.com/watch?t=935&v=tkLUJKmOjMY&feature=youtu.be\n\nEpic Creator Code: KindaFunny\n\nSubscribe And Ring The Notification Bell: \nKinda Funny: http://www.youtube.com/kindafunny?sub_confirmation=1\nKinda Funny Games: http://www.youtube.com/kindafunnygames?sub_confirmation=1\nKinda Funny Plays: http://www.youtube.com/kindafunnyplays?sub_confirmation=1\n\nGet The Shows Ad-Free On Patreon: \nKinda Funny http://www.patreon.com/KindaFunny \nKinda Funny Games http://www.patreon.com/KindaFunnyGames\n\nBuy Some Merch: http://www.kindafunny.com/store \n\nFollow Us On Twitter: http://www.twitter.com/KindaFunnyVids \n\nFollow Us On Instagram: http://instagram.com/KindaFunnyVids\n\nWatch Us Live On Twitch: http://www.twitch.tv/KindaFunnyGames\n\nListen To Our Podcasts On Your Favorite Podcast Service:\nThe Kinda Funny Podcast: https://bit.ly/3wA9GVo\nIn Review \u2013 Movies Ranked, Reviewed, & Recapped: https://bit.ly/2VAgdT7\nKinda Funny Screencast \u2013 TV & Movie Reviews Podcast: https://bit.ly/3e7yQ75\nKinda Funny Gamescast: https://bit.ly/3wBgRwg\nKinda Funny Games Daily: https://bit.ly/2T3Y3rS\nPS I Love You XOXO \u2013 A PlayStation Podcast: https://bit.ly/3r3rjvB\nKinda Funny Xcast \u2013 An Xbox Podcast: https://bit.ly/36twqvD\n\nFollow The Kinda Funny Team On Twitter:\nGreg Miller: https://twitter.com/GameOverGreggy\nTim Gettys: https://twitter.com/TimGettys\nNick Scarpino: https://twitter.com/Nick_Scarpino\nAndy Cortez: https://twitter.com/TheAndyCortez\nBlessing Adeoye: https://twitter.com/BlessingJr\nMike Howard: https://twitter.com/SnowBikeMike\nKevin Coello: https://twitter.com/KindaFunnyKevin\nJoey Noelle: https://twitter.com/joeynoelle\nBarrett Courtney: https://twitter.com/SadBoyBarrett\nRoger Pokorny: https://twitter.com/rogformer\nGreg Gettys: https://twitter.com/KindaCoolGreg\nGary Whitta: https://twitter.com/garywhitta\nParris Lilly: https://twitter.com/vicious696\nJanet Garcia: https://twitter.com/Gameonysus\nTamoor Hussain: https://twitter.com/TamoorH\n\nIn Review Intro Videos by: https://twitter.com/CameronKen\nIn Review Intro Music by: https://twitter.com/CarterHarrell",
    "published_at": 1651876206,
    "duration": 59,
    "transcript_chunks": [
        {
            "text": "i think kevin needs heels yeah i definitely need help i'm in the middle of five captain's on fire right now i died [\u00a0__\u00a0] i'm sorry kevin's dead yeah i was stood in front of fire get out of the park tell me yeah you're dead you're dead don't revive them don't revive them how do you not get oh my [\u00a0__\u00a0] [\u00a0__\u00a0] sorry guys sorry sorry i was kevin i'm going to pick up the man because they stood in fire i stood in fire oh my god oh my god i'm on fire can't we just run through fire yeah i it wasn't on fire when i started [\u00a0__\u00a0] me or fall apart oh damn it that fire doesn't [\u00a0__\u00a0] around does it no it really doesn't andy what are you [\u00a0__\u00a0] sighing about it's unbelievable it's a mechanic do you have your monitor on oh my god you're on fire again the fire on this is a simple pattern it's on and then it waits and then it goes off and then it waits [\u00a0__\u00a0]",
            "start": 0.48
        }
    ]
}